jeap_pipeline/__init__.py
jeap_pipeline/automated_staging.py
jeap_pipeline/deployment_log_model.py
jeap_pipeline/deployment_log_operations.py
jeap_pipeline/ecs_deployment_checker.py
jeap_pipeline/ecs_undeployment_checker.py
jeap_pipeline/github_dispatch_event.py
jeap_pipeline/hello_jeap.py
jeap_pipeline/message_contract_service_configuration.py
jeap_pipeline/message_contract_service_operations.py
jeap_pipeline/pact_configuration.py
jeap_pipeline/pact_operations.py
jeap_pipeline/pact_pacticipants.py
jeap_pipeline/remedy_operations.py
jeap_pipeline/test_orchestrator.py
jeap_pipeline-0.14.5.dist-info/METADATA
jeap_pipeline-0.14.5.dist-info/WHEEL
jeap_pipeline-0.14.5.dist-info/licenses/LICENSE
jeap_pipeline-0.14.5.dist-info/RECORD
