Metadata-Version: 2.4
Name: jeap_pipeline
Version: 0.14.5
Summary: A collection of Python modules and libraries for CI/CD pipelines in the jEAP context.
Project-URL: Homepage, https://github.com/jeap-admin-ch/jeap-python-pipeline-lib
Project-URL: Issues, https://github.com/jeap-admin-ch/jeap-python-pipeline-lib
Author-email: Laris Jacobs <laris.jacobs@bit.admin.ch>, Jose Alvarez Morales <jose.alvarezmorales@bit.admin.ch>, Oliver Santschi <oliver.santschi@bit.admin.ch>, Fabien Cerf <fabien.cerf@bit.admin.ch>, Matthias Fritschi <matthias.fritschi@bit.admin.ch>
License-Expression: Apache-2.0
License-File: LICENSE
Classifier: Operating System :: OS Independent
Classifier: Programming Language :: Python :: 3
Requires-Python: >=3.8
Requires-Dist: boto3==1.39.15
Requires-Dist: requests==2.32.4
Provides-Extra: dev
Requires-Dist: build==1.2.2.post1; extra == 'dev'
Requires-Dist: pip-licenses==5.0.0; extra == 'dev'
Requires-Dist: pytest==8.4.1; extra == 'dev'
Requires-Dist: twine==6.1.0; extra == 'dev'
